flexeval/__about__.py
flexeval/__init__.py
flexeval/__main__.py
flexeval/cli.py
flexeval/completions.py
flexeval/compute_metrics.py
flexeval/config.yaml
flexeval/data_loader.py
flexeval/db_utils.py
flexeval/dependency_graph.py
flexeval/eval_schema.json
flexeval/function_types.py
flexeval/helpers.py
flexeval/log_utils.py
flexeval/rubric.py
flexeval/run_utils.py
flexeval/runner.py
flexeval/classes/__init__.py
flexeval/classes/base.py
flexeval/classes/dataset.py
flexeval/classes/eval_runner.py
flexeval/classes/eval_set_run.py
flexeval/classes/jsonview.py
flexeval/classes/message.py
flexeval/classes/metric.py
flexeval/classes/thread.py
flexeval/classes/tool_call.py
flexeval/classes/turn.py
flexeval/configuration/__init__.py
flexeval/configuration/completion_functions.py
flexeval/configuration/evals.yaml
flexeval/configuration/function_metrics.py
flexeval/configuration/rubric_metrics.yaml
flexeval/io/__init__.py
flexeval/io/parsers/yaml_parser.py
flexeval/metrics/__init__.py
flexeval/metrics/access.py
flexeval/metrics/save.py
flexeval/schema/__init__.py
flexeval/schema/config_schema.py
flexeval/schema/eval_schema.py
flexeval/schema/evalrun_schema.py
flexeval/schema/rubric_schema.py
flexeval/schema/schema_utils.py
python_flexeval-0.3.0.dist-info/METADATA
python_flexeval-0.3.0.dist-info/WHEEL
python_flexeval-0.3.0.dist-info/entry_points.txt
python_flexeval-0.3.0.dist-info/licenses/LICENSE
python_flexeval-0.3.0.dist-info/RECORD
