Metadata-Version: 2.4
Name: python-flexeval
Version: 0.3.0
Summary: FlexEval is a tool for designing custom metrics, completion functions, and LLM-graded rubrics for evaluating the behavior of LLM-powered systems.
Project-URL: Homepage, https://digitalharborfoundation.github.io/FlexEval/
Project-URL: GitHub, https://github.com/DigitalHarborFoundation/FlexEval
Project-URL: Issues, https://github.com/DigitalHarborFoundation/FlexEval/issues
Author: S. Thomas Christie, Zachary Levonian, Baptiste Moreau-Pernet, Anna Rafferty, Terry Yu Tian
License-Expression: MIT
License-File: LICENSE
Keywords: conversation,education,evaluation,large language models,learning engineering
Classifier: Intended Audience :: Education
Classifier: Intended Audience :: Science/Research
Classifier: License :: OSI Approved :: MIT License
Classifier: Natural Language :: English
Classifier: Operating System :: OS Independent
Classifier: Programming Language :: Python :: 3
Classifier: Topic :: Scientific/Engineering
Requires-Python: >=3.10
Requires-Dist: flatten-json>=0.1.14
Requires-Dist: jsonschema>=4.23.0
Requires-Dist: langchain-openai>=0.3.8
Requires-Dist: langchain>=0.3.20
Requires-Dist: langgraph-checkpoint-sqlite>=2.0.6
Requires-Dist: langgraph>=0.3.6
Requires-Dist: litellm>=1.74.3
Requires-Dist: msgpack>=1.1.0
Requires-Dist: networkx>=3.4.2
Requires-Dist: openai>=1.66.0
Requires-Dist: pandas>=2.2.3
Requires-Dist: peewee>=3.17.9
Requires-Dist: pydantic>=2.10.6
Requires-Dist: python-dotenv>=1.0.1
Requires-Dist: pyyaml>=6.0.2
Requires-Dist: requests>=2.32.3
Requires-Dist: sympy>=1.13.3
Requires-Dist: textstat>=0.7.5
Requires-Dist: typer>=0.16.0
